wtprompt/__init__.py
wtprompt/core.py
wtprompt/fill.py
wtprompt/utils/basic_operations.py
wtprompt/utils/json_validator.py
wtprompt/utils/preprocessor.py
wtprompt-0.1.2.dist-info/LICENSE
wtprompt-0.1.2.dist-info/METADATA
wtprompt-0.1.2.dist-info/WHEEL
wtprompt-0.1.2.dist-info/top_level.txt
wtprompt-0.1.2.dist-info/RECORD
