Metadata-Version: 2.2
Name: wtprompt
Version: 0.1.2
Summary: A lightweight, no-nonsense library for managing your LLM prompts.
Author-email: Giovanni Alzetta <giovannialzetta@gmail.com>
License: MIT
Project-URL: Homepage, https://github.com/GivAlz/wtprompt
Classifier: Programming Language :: Python :: 3
Classifier: License :: OSI Approved :: MIT License
Classifier: Operating System :: OS Independent
Requires-Python: >=3.8
License-File: LICENSE
Requires-Dist: pydantic
Requires-Dist: Jinja2
